iap_local_receipt/__init__.py
iap_local_receipt/iap_pkcs7_verifier.py
iap_local_receipt/iap_receipt.py
iap_local_receipt/iap_receipt_parser.py
iap_local_receipt/iap_receipt_verifier.py
iap_local_receipt/rfc3339.py
iap_local_receipt/tests.py
iap_local_receipt-0.2.0.dist-info/DESCRIPTION.rst
iap_local_receipt-0.2.0.dist-info/METADATA
iap_local_receipt-0.2.0.dist-info/RECORD
iap_local_receipt-0.2.0.dist-info/WHEEL
iap_local_receipt-0.2.0.dist-info/metadata.json
iap_local_receipt-0.2.0.dist-info/top_level.txt
