Metadata-Version: 2.0
Name: iap-local-receipt
Version: 0.2.0
Summary: A library for local verification of Apple in-app receipts.
Home-page: https://github.com/SilentCircle/iap-local-receipt.git
Author: Edwin Fine
Author-email: efine@silentcircle.com
License: BSD
Keywords: apple in-app receipt verification
Platform: UNKNOWN
Classifier: License :: OSI Approved :: BSD License
Classifier: Programming Language :: Python
Classifier: Programming Language :: Python :: 2.5
Classifier: Programming Language :: Python :: 2.6
Classifier: Programming Language :: Python :: 2.7
Classifier: Programming Language :: Python :: 3.2
Classifier: Programming Language :: Python :: 3.3
Classifier: Topic :: Software Development :: Libraries :: Python Modules
Requires-Python: >=2.5
Requires-Dist: pyasn1
Requires-Dist: pyasn1-modules
Requires-Dist: pyopenssl (>=17.0.0)
